cscript/__init__.py
cscript-0.0.1.3.dist-info/COPYING
cscript-0.0.1.3.dist-info/METADATA
cscript-0.0.1.3.dist-info/WHEEL
cscript-0.0.1.3.dist-info/top_level.txt
cscript-0.0.1.3.dist-info/RECORD
