Metadata-Version: 2.1
Name: cscript
Version: 0.0.1.3
Summary: A rapid circuit creation library.
Home-page: https://github.com/Sprocketer/cscript
Author: Alex
Author-email: sprocketerdev@gmail.com
Keywords: pypi,python
Classifier: Development Status :: 1 - Planning
Classifier: Intended Audience :: Developers
Classifier: Programming Language :: Python :: 3
Classifier: Operating System :: Unix
Classifier: Operating System :: MacOS :: MacOS X
Classifier: Operating System :: Microsoft :: Windows
License-File: COPYING
Requires-Dist: numpy
